{
    "city": "林芝地区",
    "district": [
        {
            "name": "林芝县",
            "postCode": "860100"
        },
        {
            "name": "工布江达县",
            "postCode": "860200"
        },
        {
            "name": "米林县",
            "postCode": "860500"
        },
        {
            "name": "墨脱县",
            "postCode": "860700"
        },
        {
            "name": "波密县",
            "postCode": "860300"
        },
        {
            "name": "察隅县",
            "postCode": "860600"
        },
        {
            "name": "朗　县",
            "postCode": "860400"
        }
    ]
}