{
    "city":"许昌市",
    "district": [
        {
            "name": "魏都区",
            "postCode": "461000"
        },
        {
            "name": "禹州市",
            "postCode": "461670"
        },
        {
            "name": "长葛市",
            "postCode": "461500"
        },
        {
            "name": "许昌县",
            "postCode": "461100"
        },
        {
            "name": "鄢陵县",
            "postCode": "461200"
        },
        {
            "name": "襄城县",
            "postCode": "461700"
        }
    ]
}