{
    "city": "伊犁州",
    "district": [
        {
            "name": "伊宁市",
            "postCode": "835000"
        },
        {
            "name": "奎屯市",
            "postCode": "833200"
        },
        {
            "name": "伊宁县",
            "postCode": "835100"
        },
        {
            "name": "霍城县",
            "postCode": "835200"
        },
        {
            "name": "巩留县",
            "postCode": "835400"
        },
        {
            "name": "新源县",
            "postCode": "835800"
        },
        {
            "name": "昭苏县",
            "postCode": "835600"
        },
        {
            "name": "特克斯县",
            "postCode": "835500"
        },
        {
            "name": "尼勒克县",
            "postCode": "835700"
        },
        {
            "name": "察布查尔锡伯自治县",
            "postCode": "835300"
        }
    ]
}