{
    "city": "通化市",
    "district": [
        {
            "name": "东昌区",
            "postCode": "134001"
        },
        {
            "name": "二道江区",
            "postCode": "134303"
        },
        {
            "name": "梅河口市",
            "postCode": "135000"
        },
        {
            "name": "集安市",
            "postCode": "134200"
        },
        {
            "name": "通化县",
            "postCode": "134100"
        },
        {
            "name": "辉南县",
            "postCode": "135100"
        },
        {
            "name": "柳河县",
            "postCode": "135300"
        }
    ]
}