{
    "city": "白山市",
    "district": [
        {
            "name": "八道江区",
            "postCode": "134300"
        },
        {
            "name": "江源区",
            "postCode": "134700"
        },
        {
            "name": "临江市",
            "postCode": "134600"
        },
        {
            "name": "抚松县",
            "postCode": "134500"
        },
        {
            "name": "靖宇县",
            "postCode": "135200"
        },
        {
            "name": "长白朝鲜族自治县",
            "postCode": "134400"
        }
    ]
}